airflowhdi/__init__.py
airflowhdi/hooks/__init__.py
airflowhdi/hooks/azure_hdinsight_hook.py
airflowhdi/hooks/livy_batch_hook.py
airflowhdi/operators/__init__.py
airflowhdi/operators/azure_hdinsight_create_cluster_operator.py
airflowhdi/operators/azure_hdinsight_delete_cluster_operator.py
airflowhdi/operators/azure_hdinsight_ssh_operator.py
airflowhdi/operators/livy_batch_operator.py
airflowhdi/sensors/__init__.py
airflowhdi/sensors/adls_gen1_webhdfs_sensor.py
airflowhdi/sensors/azure_hdinsight_cluster_sensor.py
airflowhdi/sensors/livy_batch_sensor.py
airflowhdi/sensors/wasb_wildcard_sensor.py
airflowlivy/hooks/__init__.py
airflowlivy/hooks/livy_batch_hook.py
airflowlivy/operators/__init__.py
airflowlivy/operators/livy_batch_operator.py
airflowlivy/sensors/__init__.py
airflowlivy/sensors/livy_batch_sensor.py
airflow_hdinsight-0.0.1.3.dist-info/LICENSE
airflow_hdinsight-0.0.1.3.dist-info/METADATA
airflow_hdinsight-0.0.1.3.dist-info/WHEEL
airflow_hdinsight-0.0.1.3.dist-info/top_level.txt
airflow_hdinsight-0.0.1.3.dist-info/RECORD
