Metadata-Version: 2.1
Name: airflow-hdinsight
Version: 0.0.1.3
Summary: HDInsight provider for Airflow
Home-page: https://github.com/angadsingh/airflow-hdinsight
Author: Angad Singh
Author-email: angad.singh@trufactor.io
License: Apache Software License (http://www.apache.org/licenses/LICENSE-2.0)
Platform: UNKNOWN
Classifier: Programming Language :: Python :: 3
Classifier: License :: OSI Approved :: Apache Software License
Classifier: Operating System :: OS Independent
Requires-Python: >=3.7
Requires-Dist: azure-mgmt-hdinsight (~=1.5.1)
Requires-Dist: msrestazure (~=0.6.3)
Requires-Dist: apache-airflow (<=2.*,>=1.10.10)
Requires-Dist: azure-storage-blob (==2.1.0)
Requires-Dist: azure-storage-common (==2.1.0)
Requires-Dist: azure-storage-nspkg (==3.1.0)
Requires-Dist: azure-datalake-store
Requires-Dist: paramiko
Requires-Dist: sshtunnel
